README.rst
get_hubway_data.py
setup.cfg
setup.py
get_hubway_data.egg-info/PKG-INFO
get_hubway_data.egg-info/SOURCES.txt
get_hubway_data.egg-info/dependency_links.txt
get_hubway_data.egg-info/requires.txt
get_hubway_data.egg-info/top_level.txt