Metadata-Version: 1.0
Name: get-hubway-data
Version: 1.1
Summary: Extract data from Hubway CSVs
Home-page: UNKNOWN
Author: UNKNOWN
Author-email: UNKNOWN
License: UNKNOWN
Platform: UNKNOWN
